darklink/__init__.py
darklink/cli.py
darklink/httpfactory.py
darklink/tools/__init__.py
darklink/tools/chisel.py
darklink/tools/lazagne.py
darklink/tools/linenum.py
darklink/tools/mimikatz.py
darklink/tools/peass-ng.py
darklink/tools/privesccheck.py
darklink/tools/pspy.py
darklink/tools/runascs.py
darklink/tools/sharphound.py
darklink/tools/sysinternal.py
darklink/util.py
darklink-1.0.0.dist-info/LICENSE
darklink-1.0.0.dist-info/METADATA
darklink-1.0.0.dist-info/WHEEL
darklink-1.0.0.dist-info/entry_points.txt
darklink-1.0.0.dist-info/RECORD
