Metadata-Version: 2.1
Name: darklink
Version: 1.0.0
Summary: A tool to quickly transfer a file to or from a compromised system
Home-page: https://github.com/vedard/darklink
License: GPL-3.0-only
Keywords: security,pentesting,ctf,tool
Author: vedard
Requires-Python: >=3.11,<4.0
Classifier: License :: OSI Approved :: GNU General Public License v3 (GPLv3)
Classifier: Programming Language :: Python :: 3
Classifier: Programming Language :: Python :: 3.11
Classifier: Programming Language :: Python :: 3.12
Classifier: Topic :: Security
Requires-Dist: click (>=8.1.7,<9.0.0)
Requires-Dist: requests (>=2.31.0,<3.0.0)
